LICENSE
MANIFEST.in
README.md
pyproject.toml
setup.py
hpfrec/__init__.py
hpfrec/cython_double.pxi
hpfrec/cython_double_nonwindows.pyx
hpfrec/cython_double_windows.pyx
hpfrec/cython_float.pxi
hpfrec/cython_float_nonwindows.pyx
hpfrec/cython_float_windows.pyx
hpfrec/cython_loops.pxi
hpfrec/return0.pyx
hpfrec/return1.pyx
hpfrec.egg-info/PKG-INFO
hpfrec.egg-info/SOURCES.txt
hpfrec.egg-info/dependency_links.txt
hpfrec.egg-info/top_level.txt